bmkcc
