Metadata-Version: 2.1
Name: bmk-cell-calling
Version: 0.2.2
Summary: Analysis of sequencing data of single cell.
Home-page: https://github.com/wangjianshou/single-cell-calling
Author: Wang Jianshou
Author-email: wangjs@biomarker.com.cn
License: UNKNOWN
Platform: UNKNOWN
Requires-Python: >=3.8, <3.10
